nookipedia/__init__.py
nookipedia/api/__init__.py
nookipedia/api/api.py
nookipedia/api/cached_api.py
nookipedia/models/__init__.py
nookipedia/models/bug.py
nookipedia/models/cached_object.py
nookipedia/models/common.py
nookipedia/models/fish.py
nookipedia/models/fossil.py
nookipedia/models/villager.py
nookipedia/models/villager_old.py
nookipedia/nookipedia.py
async_nookipedia-1.0.1.dist-info/LICENSE
async_nookipedia-1.0.1.dist-info/WHEEL
async_nookipedia-1.0.1.dist-info/METADATA
async_nookipedia-1.0.1.dist-info/RECORD
