Metadata-Version: 2.1
Name: async-nookipedia
Version: 1.0.1
Summary: async API wrapper for Nookipedia API written in python
Home-page: https://github.com/makupi/async-nookipedia
License: GPL-3.0
Author: makubob
Author-email: makupi@icloud.com
Requires-Python: >=3.7,<4.0
Classifier: License :: OSI Approved :: GNU General Public License v3 (GPLv3)
Classifier: Programming Language :: Python :: 3
Classifier: Programming Language :: Python :: 3.7
Classifier: Programming Language :: Python :: 3.8
Classifier: Programming Language :: Python :: 3.9
Requires-Dist: aiohttp (>=3.6.2,<4.0.0)
Requires-Dist: importlib_metadata (>=1.6.0,<2.0.0)
Requires-Dist: pydantic (>=1.8.1,<2.0.0)
Requires-Dist: python-dateutil (>=2.8.1,<3.0.0)
Requires-Dist: sphinx (>=3.0.3,<4.0.0)
Project-URL: Repository, https://github.com/makupi/async-nookipedia
